{
  "theme.font.size": "16",
  "theme.bar.buttons.spacing": "0.25em",
  "theme.bar.buttons.radius": "15px",
  "theme.bar.floating": false,
  "bar.launcher.icon": "",
  "bar.workspaces.workspaces": 5,
  "bar.workspaces.monitorSpecific": true,
  "theme.bar.buttons.windowtitle.spacing": "1em",
  "menus.clock.time.military": true,
  "menus.clock.weather.unit": "metric",
  "menus.clock.weather.key": "4afb0b6cb609401da30231750242807",
  "menus.dashboard.powermenu.avatar.image": "/home/orangc/Pictures/walls/yohoho.jpg",
  "menus.dashboard.directories.left.directory1.command": "bash -c \"thunar $HOME/Downloads/\"",
  "menus.dashboard.directories.left.directory2.label": "󰉏  Videos",
  "menus.dashboard.directories.left.directory2.command": "bash -c \"thunar $HOME/Videos/\"",
  "menus.dashboard.directories.left.directory3.command": "bash -c \"thunar $HOME/Projects/\"",
  "menus.dashboard.directories.right.directory1.command": "bash -c \"thunar $HOME/Documents/\"",
  "menus.dashboard.directories.right.directory1.label": "󱧶  Documents",
  "menus.dashboard.directories.left.directory3.label": "󰚝  Projects",
  "menus.dashboard.directories.left.directory1.label": "󰉍  Downloads",
  "menus.dashboard.directories.right.directory2.label": "󰉏  Pictures",
  "menus.dashboard.directories.right.directory2.command": "bash -c \"thunar $HOME/Pictures/\"",
  "menus.dashboard.directories.right.directory3.label": "󱂵  Home",
  "menus.dashboard.directories.right.directory3.command": "bash -c \"thunar $HOME/\"",
  "theme.bar.menus.monochrome": false,
  "theme.bar.menus.card_radius": "24px",
  "theme.bar.menus.border.radius": "24px",
  "theme.bar.transparent": true,
  "theme.bar.buttons.monochrome": false,
  "theme.notification.close_button.background": "#f38ba8",
  "bar.clock.format": "󰃭  %A %d     %H:%M",
  "bar.notifications.show_total": true,
  "theme.bar.buttons.notifications.spacing": "0.5em",
  "theme.bar.buttons.media.spacing": "1px",
  "theme.bar.margin_top": ".1em",
  "theme.bar.border_radius": "15px",
  "theme.bar.margin_sides": "0em",
  "theme.bar.outer_spacing": ".5em",
  "bar.workspaces.show_icons": false,
  "bar.bluetooth.label": true,
  "bar.network.label": true,
  "bar.layouts": {
    "0": {
      "left": [
        "dashboard",
        "workspaces",
        "volume"
      ],
      "middle": [
        "windowtitle"
      ],
      "right": [
        "network",
        "bluetooth",
        "systray",
        "clock"
      ]
    }
  },
  "theme.bar.buttons.clock.text": "#f38ba8",
  "theme.bar.buttons.clock.icon": "#f38ba8",
  "theme.bar.buttons.bluetooth.text": "#fab387",
  "theme.bar.buttons.bluetooth.icon": "#fab387",
  "theme.bar.buttons.network.text": "#f9e2af",
  "theme.bar.buttons.network.icon": "#f9e2af",
  "theme.bar.buttons.windowtitle.text": "#a6e3a1",
  "theme.bar.buttons.windowtitle.icon": "#a6e3a1",
  "theme.bar.buttons.volume.text": "#74c6ec",
  "theme.bar.buttons.volume.icon": "#74c6ec",
  "theme.bar.buttons.workspaces.available": "#caa6f7",
  "theme.bar.buttons.workspaces.occupied": "#caa6f7",
  "theme.bar.buttons.workspaces.active": "#f5c2e7",
  "theme.bar.menus.menu.clock.background.color": "#11111b",
  "theme.bar.menus.menu.clock.time.time": "#f38ba8",
  "theme.bar.menus.menu.clock.calendar.yearmonth": "#f38ba8",
  "theme.bar.menus.menu.clock.weather.icon": "#f9e2af",
  "theme.bar.menus.menu.clock.weather.temperature": "#a6e3a1",
  "theme.bar.menus.menu.clock.weather.status": "#89dbeb",
  "theme.bar.menus.menu.clock.weather.thermometer.extremelyhot": "#cdd6f4",
  "theme.bar.menus.menu.clock.weather.stats": "#f9e2af",
  "theme.bar.menus.menu.clock.weather.hourly.temperature": "#cdd6f4",
  "theme.bar.menus.menu.clock.weather.hourly.icon": "#cdd6f4",
  "theme.bar.menus.menu.clock.weather.hourly.time": "#cdd6f4",
  "theme.bar.menus.menu.clock.calendar.weekdays": "#a6e3a1",
  "theme.bar.buttons.clock.hover": "#45475a",
  "theme.bar.buttons.notifications.hover": "#45475a",
  "theme.bar.buttons.battery.hover": "#45475a",
  "theme.bar.buttons.systray.hover": "#45475a",
  "theme.bar.buttons.bluetooth.hover": "#45475a",
  "theme.bar.buttons.network.hover": "#45475a",
  "theme.bar.buttons.volume.hover": "#45475a",
  "theme.bar.buttons.media.hover": "#45475a",
  "theme.bar.buttons.windowtitle.hover": "#45475a",
  "theme.bar.menus.menu.bluetooth.label.color": "#fab387",
  "theme.bar.menus.menu.bluetooth.listitems.active": "#fab387",
  "theme.bar.menus.menu.bluetooth.icons.active": "#fab387",
  "theme.bar.menus.menu.bluetooth.iconbutton.active": "#fab387",
  "theme.bar.menus.menu.bluetooth.switch.enabled": "#fab387",
  "theme.bar.menus.menu.network.iconbuttons.active": "#f9e2af",
  "theme.bar.menus.menu.network.icons.active": "#f9e2af",
  "theme.bar.menus.menu.network.listitems.active": "#f9e2af",
  "theme.bar.menus.menu.network.label.color": "#f9e2af",
  "theme.bar.menus.menu.volume.label.color": "#74c6ec",
  "theme.bar.menus.menu.volume.listitems.active": "#74c6ec",
  "theme.bar.menus.menu.volume.iconbutton.active": "#74c6ec",
  "theme.bar.menus.menu.volume.icons.active": "#74c6ec",
  "theme.bar.menus.menu.volume.audio_slider.primary": "#74c6ec",
  "theme.bar.menus.menu.volume.input_slider.primary": "#74c6ec"
}